Metadata-Version: 2.1
Name: modcondor
Version: 0.1
Summary: Ejercicio de paquetes de python
Author: jhony
Author-email: jhony28bravo@gmail.com
License: MIT
